threddar/__init__.py
threddar/rethread.py
threddar-0.0.4.dist-info/LICENSE
threddar-0.0.4.dist-info/METADATA
threddar-0.0.4.dist-info/WHEEL
threddar-0.0.4.dist-info/top_level.txt
threddar-0.0.4.dist-info/RECORD
