Metadata-Version: 2.1
Name: threddar
Version: 0.0.4
Summary: Threads, Threads, and Threads.
Author: S. C. The Mysterious
Author-email: "S. C. The Mysterious" <author@example.com>
Project-URL: Homepage, https://github.com/mooocow123/threddar
Project-URL: Issues, https://github.com/mooocow123/threddar/issues
Classifier: Programming Language :: Python :: 3
Classifier: License :: OSI Approved :: MIT License
Classifier: Operating System :: OS Independent
Requires-Python: >=3.9
License-File: LICENSE
